cognitiveai/__init__.py
cognitiveai_sdk-0.2.0.dist-info/METADATA
cognitiveai_sdk-0.2.0.dist-info/WHEEL
cognitiveai_sdk-0.2.0.dist-info/top_level.txt
cognitiveai_sdk-0.2.0.dist-info/RECORD
